{"births":[{"d":"2026-05-16","aid":"199881","g":"undetermined","s":"Oakridge Habitat","e":"Lake Dale Run"},{"d":"2026-04-16","aid":"195341","g":"male","s":"Oakridge Habitat","e":"Holly Holt Enclosure"},{"d":"2025-05-12","aid":"125538","g":"male","s":"Oakridge Habitat","e":"Slate Heath Habitat"}],"deaths":[{"d":"2026-04-24","aid":"31982","idn":"Name","idv":"Lennox 65","g":"male","s":"Oakridge Habitat","e":"Holly Holt Enclosure","m":"Natural","c":"Fresh","y":"Completed","a":5},{"d":"2025-05-17","aid":"125538","g":"male","s":"Oakridge Habitat","e":"Slate Heath Habitat","m":"Acute Disease","c":"Fresh","y":"Completed","a":0},{"d":"2025-03-25","aid":"86732","idn":"Name","idv":"Teagan 87","g":"male","s":"Oakridge Habitat","e":"Cedar Mere Roost","m":"Natural","c":"Fresh","y":"Pending"},{"d":"2025-02-23","aid":"86734","idn":"Name","idv":"Tatum 68","g":"female","s":"Mossvale Rescue Centre","e":"Bramble Hollow Aviary","m":"Natural","c":"Fresh","y":"Pending"},{"d":"2024-09-07","aid":"53654","g":"male","s":"Oakridge Habitat","e":"Vale Gate Terrarium","m":"Natural","c":"Fresh","y":"Pending"},{"d":"2024-08-09","aid":"53651","g":"undetermined","s":"Oakridge Habitat","e":"Oak Bank Coop","m":"Natural","c":"Fresh","y":"Pending"},{"d":"2024-07-02","aid":"31979","g":"female","s":"Oakridge Habitat","e":"Marsh Meadow Coop","m":"Natural","c":"Fresh","y":"Pending"}]}