{"births":[{"d":"2026-04-20","aid":"196758","g":"undetermined","s":"Cedarbrook Wildlife Haven","e":"Holly Grove Roost"},{"d":"2026-04-20","aid":"196757","g":"undetermined","s":"Cedarbrook Wildlife Haven","e":"Holly Grove Roost"}],"deaths":[{"d":"2026-04-28","aid":"149740","idn":"RN","idv":"BOF BN599 10.0 24 007","g":"undetermined","s":"Cedarbrook Wildlife Haven","e":"Holly Grove Roost","m":"Under Treatment","c":"Fresh","y":"Pending","sv":271},{"d":"2026-04-06","aid":"149738","idn":"RN","idv":"BOF BN 599 10.0 24 011","g":"undetermined","s":"Cedarbrook Wildlife Haven","e":"Holly Grove Roost","m":"Undetermined","c":"Fresh","y":"Pending","sv":249},{"d":"2026-01-14","aid":"149732","idn":"RN","idv":"KEVB3149.0200006","g":"female","s":"Cedarbrook Wildlife Haven","e":"Ivy Reach Coop","m":"Indeterminate","c":"Fresh","y":"Completed","sv":167},{"d":"2025-12-01","aid":"94167","idn":"RN","idv":"KEVOV62312.012008","g":"undetermined","s":"Cedarbrook Wildlife Haven","e":"Oak Reach Pen","m":"Under Treatment","c":"Fresh","y":"Pending","sv":308},{"d":"2025-09-10","aid":"145288","idn":"RN","idv":"SBI WF 38","g":"undetermined","s":"Cedarbrook Wildlife Haven","e":"Pine Wold Vivarium","m":"Undetermined","c":"Fresh","y":"Pending","sv":63},{"d":"2025-08-11","aid":"149734","idn":"RN","idv":"224398BEC8.019009","g":"undetermined","s":"Cedarbrook Wildlife Haven","e":"Ivy Reach Coop","m":"Undetermined","c":"Fresh","y":"Pending","sv":11},{"d":"2025-07-18","aid":"145314","g":"undetermined","s":"Cedarbrook Wildlife Haven","e":"Oak Reach Pen","m":"Undetermined","c":"Fresh","y":"Pending","sv":9}]}